{"file":"Rooster_Ani_tex.png","mc":{"Rooster_Ani":{"frames":[{"y":-256,"duration":1,"res":"rooster_eat_anim_0","x":-284},{"y":-260,"duration":1,"res":"rooster_eat_anim_1","x":-281},{"y":-262,"duration":1,"res":"rooster_eat_anim_2","x":-279},{"y":-263,"duration":1,"res":"rooster_eat_anim_3","x":-276},{"y":-263,"duration":1,"res":"rooster_eat_anim_4","x":-273},{"y":-262,"duration":1,"res":"rooster_eat_anim_5","x":-270},{"y":-260,"duration":1,"res":"rooster_eat_anim_6","x":-268},{"y":-259,"duration":1,"res":"rooster_eat_anim_7","x":-265},{"y":-254,"duration":1,"res":"rooster_eat_anim_8","x":-262},{"y":-244,"duration":1,"res":"rooster_eat_anim_9","x":-259},{"y":-232,"duration":1,"res":"rooster_eat_anim_10","x":-257},{"y":-229,"duration":1,"res":"rooster_eat_anim_11","x":-257},{"y":-237,"duration":1,"res":"rooster_eat_anim_12","x":-256},{"y":-212,"duration":1,"res":"rooster_eat_anim_13","x":-282},{"y":-228,"duration":1,"res":"rooster_eat_anim_14","x":-311},{"y":-266,"duration":1,"res":"rooster_eat_anim_15","x":-384},{"y":-283,"duration":1,"res":"rooster_eat_anim_16","x":-462},{"y":-289,"duration":1,"res":"rooster_eat_anim_17","x":-473},{"y":-295,"duration":1,"res":"rooster_eat_anim_18","x":-481},{"y":-300,"duration":1,"res":"rooster_eat_anim_19","x":-484},{"y":-307,"duration":1,"res":"rooster_eat_anim_20","x":-489},{"y":-315,"duration":1,"res":"rooster_eat_anim_21","x":-491},{"y":-299,"duration":1,"res":"rooster_eat_anim_22","x":-465},{"y":-287,"duration":1,"res":"rooster_eat_anim_23","x":-421},{"y":-278,"duration":1,"res":"rooster_eat_anim_24","x":-368},{"y":-265,"duration":1,"res":"rooster_eat_anim_25","x":-354},{"y":-253,"duration":1,"res":"rooster_eat_anim_26","x":-328},{"y":-256,"duration":1,"res":"rooster_eat_anim_27","x":-358},{"y":-256,"duration":1,"res":"rooster_eat_anim_28","x":-378},{"y":-271,"duration":1,"res":"rooster_eat_anim_29","x":-404},{"y":-283,"duration":1,"res":"rooster_eat_anim_30","x":-462},{"y":-289,"duration":1,"res":"rooster_eat_anim_31","x":-473},{"y":-295,"duration":1,"res":"rooster_eat_anim_32","x":-481},{"y":-300,"duration":1,"res":"rooster_eat_anim_33","x":-484},{"y":-307,"duration":1,"res":"rooster_eat_anim_34","x":-489},{"y":-315,"duration":1,"res":"rooster_eat_anim_35","x":-491},{"y":-299,"duration":1,"res":"rooster_eat_anim_36","x":-465},{"y":-287,"duration":1,"res":"rooster_eat_anim_37","x":-421},{"y":-278,"duration":1,"res":"rooster_eat_anim_38","x":-368},{"y":-265,"duration":1,"res":"rooster_eat_anim_39","x":-354},{"y":-253,"duration":1,"res":"rooster_eat_anim_40","x":-328},{"y":-256,"duration":1,"res":"rooster_eat_anim_41","x":-364},{"y":-256,"duration":1,"res":"rooster_eat_anim_42","x":-389},{"y":-271,"duration":1,"res":"rooster_eat_anim_43","x":-411},{"y":-283,"duration":1,"res":"rooster_eat_anim_44","x":-462},{"y":-295,"duration":1,"res":"rooster_eat_anim_45","x":-471},{"y":-311,"duration":1,"res":"rooster_eat_anim_46","x":-476},{"y":-335,"duration":1,"res":"rooster_eat_anim_47","x":-475},{"y":-368,"duration":1,"res":"rooster_eat_anim_48","x":-468},{"y":-400,"duration":1,"res":"rooster_eat_anim_49","x":-457},{"y":-367,"duration":1,"res":"rooster_eat_anim_50","x":-433},{"y":-328,"duration":1,"res":"rooster_eat_anim_51","x":-392},{"y":-293,"duration":1,"res":"rooster_eat_anim_52","x":-335},{"y":-279,"duration":1,"res":"rooster_eat_anim_53","x":-294},{"y":-301,"duration":1,"res":"rooster_eat_anim_54","x":-284},{"y":-295,"duration":1,"res":"rooster_eat_anim_55","x":-283},{"y":-287,"duration":1,"res":"rooster_eat_anim_56","x":-283},{"y":-274,"duration":1,"res":"rooster_eat_anim_57","x":-283},{"y":-254,"duration":1,"res":"rooster_eat_anim_58","x":-282},{"y":-247,"duration":1,"res":"rooster_eat_anim_59","x":-282},{"y":-240,"duration":1,"res":"rooster_eat_anim_60","x":-282},{"y":-237,"duration":1,"res":"rooster_eat_anim_61","x":-283},{"y":-234,"duration":1,"res":"rooster_eat_anim_62","x":-283},{"y":-232,"duration":1,"res":"rooster_eat_anim_63","x":-283},{"y":-234,"duration":1,"res":"rooster_eat_anim_64","x":-283},{"y":-237,"duration":1,"res":"rooster_eat_anim_65","x":-283},{"y":-241,"duration":1,"res":"rooster_eat_anim_66","x":-283},{"y":-249,"duration":1,"res":"rooster_eat_anim_67","x":-284},{"y":-226,"duration":1,"res":"rooster_walk_anim_0","x":-283},{"y":-223,"duration":1,"res":"rooster_walk_anim_1","x":-283},{"y":-220,"duration":1,"res":"rooster_walk_anim_2","x":-283},{"y":-216,"duration":1,"res":"rooster_walk_anim_3","x":-284},{"y":-213,"duration":1,"res":"rooster_walk_anim_4","x":-284},{"y":-212,"duration":1,"res":"rooster_walk_anim_5","x":-284},{"y":-213,"duration":1,"res":"rooster_walk_anim_6","x":-284},{"y":-214,"duration":1,"res":"rooster_walk_anim_7","x":-284},{"y":-216,"duration":1,"res":"rooster_walk_anim_8","x":-284},{"y":-219,"duration":1,"res":"rooster_walk_anim_9","x":-284},{"y":-223,"duration":1,"res":"rooster_walk_anim_10","x":-284},{"y":-226,"duration":1,"res":"rooster_walk_anim_11","x":-284},{"y":-229,"duration":1,"res":"rooster_walk_anim_12","x":-284},{"y":-227,"duration":1,"res":"rooster_walk_anim_13","x":-284},{"y":-227,"duration":1,"res":"rooster_walk_anim_14","x":-283},{"y":-227,"duration":1,"res":"rooster_walk_anim_15","x":-283},{"y":-226,"duration":1,"res":"rooster_walk_anim_16","x":-283},{"y":-223,"duration":1,"res":"rooster_walk_anim_17","x":-283},{"y":-220,"duration":1,"res":"rooster_walk_anim_18","x":-283},{"y":-216,"duration":1,"res":"rooster_walk_anim_19","x":-284},{"y":-213,"duration":1,"res":"rooster_walk_anim_20","x":-284},{"y":-212,"duration":1,"res":"rooster_walk_anim_21","x":-284},{"y":-213,"duration":1,"res":"rooster_walk_anim_22","x":-284},{"y":-214,"duration":1,"res":"rooster_walk_anim_23","x":-284},{"y":-216,"duration":1,"res":"rooster_walk_anim_24","x":-284},{"y":-219,"duration":1,"res":"rooster_walk_anim_25","x":-284},{"y":-223,"duration":1,"res":"rooster_walk_anim_26","x":-284},{"y":-226,"duration":1,"res":"rooster_walk_anim_27","x":-284},{"y":-229,"duration":1,"res":"rooster_walk_anim_28","x":-284},{"y":-227,"duration":1,"res":"rooster_walk_anim_29","x":-284},{"y":-227,"duration":1,"res":"rooster_walk_anim_30","x":-283},{"y":-227,"duration":1,"res":"rooster_walk_anim_31","x":-283},{"y":-203,"duration":1,"res":"rooster_idle_sleep_anim_0","x":-285},{"y":-203,"duration":1,"res":"rooster_idle_sleep_anim_1","x":-285},{"y":-204,"duration":1,"res":"rooster_idle_sleep_anim_2","x":-285},{"y":-204,"duration":1,"res":"rooster_idle_sleep_anim_3","x":-285},{"y":-204,"duration":1,"res":"rooster_idle_sleep_anim_4","x":-285},{"y":-204,"duration":1,"res":"rooster_idle_sleep_anim_5","x":-285},{"y":-205,"duration":1,"res":"rooster_idle_sleep_anim_6","x":-285},{"y":-205,"duration":1,"res":"rooster_idle_sleep_anim_7","x":-285},{"y":-205,"duration":1,"res":"rooster_idle_sleep_anim_8","x":-285},{"y":-205,"duration":1,"res":"rooster_idle_sleep_anim_9","x":-285},{"y":-204,"duration":1,"res":"rooster_idle_sleep_anim_10","x":-285},{"y":-204,"duration":1,"res":"rooster_idle_sleep_anim_11","x":-285},{"y":-204,"duration":1,"res":"rooster_idle_sleep_anim_12","x":-285},{"y":-203,"duration":1,"res":"rooster_idle_sleep_anim_13","x":-285},{"y":-203,"duration":1,"res":"rooster_idle_sleep_anim_14","x":-285},{"y":-203,"duration":1,"res":"rooster_idle_sleep_anim_15","x":-285},{"y":-202,"duration":1,"res":"rooster_idle_sleep_anim_16","x":-285},{"y":-202,"duration":1,"res":"rooster_idle_sleep_anim_17","x":-285},{"y":-202,"duration":1,"res":"rooster_idle_sleep_anim_18","x":-285},{"y":-202,"duration":1,"res":"rooster_idle_sleep_anim_19","x":-285},{"y":-202,"duration":1,"res":"rooster_idle_sleep_anim_20","x":-285},{"y":-202,"duration":1,"res":"rooster_idle_sleep_anim_21","x":-285},{"y":-201,"duration":1,"res":"rooster_idle_sleep_anim_22","x":-285},{"y":-201,"duration":1,"res":"rooster_idle_sleep_anim_23","x":-285},{"y":-201,"duration":1,"res":"rooster_idle_sleep_anim_24","x":-285},{"y":-201,"duration":1,"res":"rooster_idle_sleep_anim_25","x":-285},{"y":-200,"duration":1,"res":"rooster_idle_sleep_anim_26","x":-285},{"y":-200,"duration":1,"res":"rooster_idle_sleep_anim_27","x":-285},{"y":-200,"duration":1,"res":"rooster_idle_sleep_anim_28","x":-285},{"y":-200,"duration":1,"res":"rooster_idle_sleep_anim_29","x":-285},{"y":-200,"duration":1,"res":"rooster_idle_sleep_anim_30","x":-285},{"y":-201,"duration":1,"res":"rooster_idle_sleep_anim_31","x":-285},{"y":-201,"duration":1,"res":"rooster_idle_sleep_anim_32","x":-285},{"y":-202,"duration":1,"res":"rooster_idle_sleep_anim_33","x":-285},{"y":-202,"duration":1,"res":"rooster_idle_sleep_anim_34","x":-285},{"y":-202,"duration":1,"res":"rooster_idle_sleep_anim_35","x":-285},{"y":-202,"duration":1,"res":"rooster_idle_sleep_anim_36","x":-285},{"y":-203,"duration":1,"res":"rooster_idle_sleep_anim_37","x":-285},{"y":-203,"duration":1,"res":"rooster_idle_sleep_anim_38","x":-285},{"y":-203,"duration":1,"res":"rooster_idle_sleep_anim_39","x":-285},{"y":-262,"duration":1,"res":"rooster_run_anim_0","x":-307},{"y":-241,"duration":1,"res":"rooster_run_anim_1","x":-307},{"y":-220,"duration":1,"res":"rooster_run_anim_2","x":-307},{"y":-218,"duration":1,"res":"rooster_run_anim_3","x":-307},{"y":-216,"duration":1,"res":"rooster_run_anim_4","x":-307},{"y":-238,"duration":1,"res":"rooster_run_anim_5","x":-307},{"y":-260,"duration":1,"res":"rooster_run_anim_6","x":-307},{"y":-261,"duration":1,"res":"rooster_run_anim_7","x":-307},{"y":-262,"duration":1,"res":"rooster_run_anim_8","x":-307},{"y":-241,"duration":1,"res":"rooster_run_anim_9","x":-307},{"y":-220,"duration":1,"res":"rooster_run_anim_10","x":-307},{"y":-218,"duration":1,"res":"rooster_run_anim_11","x":-307},{"y":-216,"duration":1,"res":"rooster_run_anim_12","x":-307},{"y":-238,"duration":1,"res":"rooster_run_anim_13","x":-307},{"y":-260,"duration":1,"res":"rooster_run_anim_14","x":-307},{"y":-261,"duration":1,"res":"rooster_run_anim_15","x":-307},{"y":-253,"duration":1,"res":"rooster_idle_anim_0","x":-284},{"y":-254,"duration":1,"res":"rooster_idle_anim_1","x":-284},{"y":-255,"duration":1,"res":"rooster_idle_anim_2","x":-284},{"y":-255,"duration":1,"res":"rooster_idle_anim_3","x":-284},{"y":-256,"duration":1,"res":"rooster_idle_anim_4","x":-284},{"y":-257,"duration":1,"res":"rooster_idle_anim_5","x":-284},{"y":-257,"duration":1,"res":"rooster_idle_anim_6","x":-284},{"y":-258,"duration":1,"res":"rooster_idle_anim_7","x":-284},{"y":-258,"duration":1,"res":"rooster_idle_anim_8","x":-284},{"y":-259,"duration":1,"res":"rooster_idle_anim_9","x":-284},{"y":-259,"duration":1,"res":"rooster_idle_anim_10","x":-284},{"y":-258,"duration":1,"res":"rooster_idle_anim_11","x":-284},{"y":-258,"duration":1,"res":"rooster_idle_anim_12","x":-284},{"y":-257,"duration":1,"res":"rooster_idle_anim_13","x":-284},{"y":-257,"duration":1,"res":"rooster_idle_anim_14","x":-284},{"y":-256,"duration":1,"res":"rooster_idle_anim_15","x":-284},{"y":-256,"duration":1,"res":"rooster_idle_anim_16","x":-284},{"y":-255,"duration":1,"res":"rooster_idle_anim_17","x":-284},{"y":-255,"duration":1,"res":"rooster_idle_anim_18","x":-284},{"y":-255,"duration":1,"res":"rooster_idle_anim_19","x":-284},{"y":-255,"duration":1,"res":"rooster_idle_anim_20","x":-284},{"y":-254,"duration":1,"res":"rooster_idle_anim_21","x":-284},{"y":-253,"duration":1,"res":"rooster_idle_anim_22","x":-284},{"y":-252,"duration":1,"res":"rooster_idle_anim_23","x":-284},{"y":-252,"duration":1,"res":"rooster_idle_anim_24","x":-284},{"y":-251,"duration":1,"res":"rooster_idle_anim_25","x":-284},{"y":-251,"duration":1,"res":"rooster_idle_anim_26","x":-284},{"y":-250,"duration":1,"res":"rooster_idle_anim_27","x":-284},{"y":-250,"duration":1,"res":"rooster_idle_anim_28","x":-284},{"y":-249,"duration":1,"res":"rooster_idle_anim_29","x":-284},{"y":-249,"duration":1,"res":"rooster_idle_anim_30","x":-284},{"y":-249,"duration":1,"res":"rooster_idle_anim_31","x":-284},{"y":-250,"duration":1,"res":"rooster_idle_anim_32","x":-284},{"y":-251,"duration":1,"res":"rooster_idle_anim_33","x":-284},{"y":-251,"duration":1,"res":"rooster_idle_anim_34","x":-284},{"y":-252,"duration":1,"res":"rooster_idle_anim_35","x":-284},{"y":-252,"duration":1,"res":"rooster_idle_anim_36","x":-284},{"y":-252,"duration":1,"res":"rooster_idle_anim_37","x":-284},{"y":-252,"duration":1,"res":"rooster_idle_anim_38","x":-284},{"y":-253,"duration":1,"res":"rooster_idle_anim_39","x":-284}],"labels":[{"end":68,"frame":1,"name":"rooster_eat_anim"},{"end":100,"frame":69,"name":"rooster_walk_anim"},{"end":140,"frame":101,"name":"rooster_idle_sleep_anim"},{"end":156,"frame":141,"name":"rooster_run_anim"},{"end":196,"frame":157,"name":"rooster_idle_anim"}],"frameRate":24,"events":[]}},"res":{}}